KnativeYunYuanshengYingyongKaifaZhinan/README.md
KnativeYunYuanshengYingyongKaifaZhinan/__init__.py
KnativeYunYuanshengYingyongKaifaZhinan/__main__.py
KnativeYunYuanshengYingyongKaifaZhinan/file.pdf
KnativeYunYuanshengYingyongKaifaZhinan/index.html
knative_yun_yuansheng_yingyong_kaifa_zhinan-2024.3.6.0.dist-info/METADATA
knative_yun_yuansheng_yingyong_kaifa_zhinan-2024.3.6.0.dist-info/WHEEL
knative_yun_yuansheng_yingyong_kaifa_zhinan-2024.3.6.0.dist-info/entry_points.txt
knative_yun_yuansheng_yingyong_kaifa_zhinan-2024.3.6.0.dist-info/top_level.txt
knative_yun_yuansheng_yingyong_kaifa_zhinan-2024.3.6.0.dist-info/RECORD
